gazedetector/__init__.py
gazedetector/app.py
gazedetector/gaze_detector.py
gazedetector-1.1.0.dist-info/LICENSE
gazedetector-1.1.0.dist-info/METADATA
gazedetector-1.1.0.dist-info/WHEEL
gazedetector-1.1.0.dist-info/top_level.txt
gazedetector-1.1.0.dist-info/RECORD
